malti_telemetry/__init__.py
malti_telemetry/core.py
malti_telemetry/middleware.py
malti_telemetry/utils.py
malti_telemetry-1.0.4.dist-info/licenses/LICENSE
malti_telemetry-1.0.4.dist-info/METADATA
malti_telemetry-1.0.4.dist-info/WHEEL
malti_telemetry-1.0.4.dist-info/top_level.txt
malti_telemetry-1.0.4.dist-info/RECORD
