Metadata-Version: 2.4
Name: malti-telemetry
Version: 1.0.4
Summary: A Python library for collecting and sending telemetry data to Malti server
Maintainer-email: smuzy <malti@muzy.dev>
License-Expression: MIT
Project-URL: Homepage, https://github.com/muzy/malti-telemetry/
Project-URL: Repository, https://github.com/muzy/malti-telemetry/
Project-URL: Issues, https://github.com/muzy/malti-telemetry/issues
Project-URL: Changelog, https://github.com/muzy/malti-telemetry/releases
Keywords: telemetry,monitoring,fastapi,analytics,api,self-hosted,starlette
Classifier: Development Status :: 5 - Production/Stable
Classifier: Intended Audience :: Developers
Classifier: Operating System :: OS Independent
Classifier: Programming Language :: Python :: 3
Classifier: Programming Language :: Python :: 3.11
Classifier: Programming Language :: Python :: 3.12
Classifier: Framework :: FastAPI
Classifier: Topic :: System :: Monitoring
Classifier: Topic :: Internet :: WWW/HTTP :: HTTP Servers
Requires-Python: >=3.11
License-File: LICENSE
Requires-Dist: httpx>=0.24.0
Requires-Dist: starlette>=0.40.0
Provides-Extra: dev
Requires-Dist: pytest>=7.0.0; extra == "dev"
Requires-Dist: pytest-asyncio>=0.21.0; extra == "dev"
Requires-Dist: pytest-cov>=4.0.0; extra == "dev"
Requires-Dist: black>=23.0.0; extra == "dev"
Requires-Dist: isort>=5.12.0; extra == "dev"
Requires-Dist: mypy>=1.0.0; extra == "dev"
Requires-Dist: flake8>=6.0.0; extra == "dev"
Requires-Dist: pre-commit>=3.0.0; extra == "dev"
Requires-Dist: fastapi>=0.100.0; extra == "dev"
Provides-Extra: docs
Requires-Dist: sphinx>=5.0.0; extra == "docs"
Requires-Dist: sphinx-rtd-theme>=1.2.0; extra == "docs"
Dynamic: license-file
